AUTHORS.rst
LICENSE
MANIFEST.in
README.rst
setup.cfg
setup.py
django_saml2_auth/__init__.py
django_saml2_auth/urls.py
django_saml2_auth/views.py
django_saml2_auth/templates/django_saml2_auth/denied.html
django_saml2_auth/templates/django_saml2_auth/signout.html
quantum_django_saml2_auth.egg-info/PKG-INFO
quantum_django_saml2_auth.egg-info/SOURCES.txt
quantum_django_saml2_auth.egg-info/dependency_links.txt
quantum_django_saml2_auth.egg-info/requires.txt
quantum_django_saml2_auth.egg-info/top_level.txt