Metadata-Version: 1.1
Name: quantum-django-saml2-auth
Version: 2.2.1
Summary: Django SAML2 Authentication Made Easy. Easily integrate with SAML2 SSO identity providers like Okta
Home-page: https://github.com/fangli/django-saml2-auth
Author: Fang Li
Author-email: surivlee+djsaml2auth@gmail.com
License: Apache 2.0
Keywords: Django SAML2 Authentication Made Easy,integrate with SAML2 SSO such as Okta easily
Platform: UNKNOWN
Classifier: Development Status :: 5 - Production/Stable
Classifier: Intended Audience :: Developers
Classifier: Topic :: Software Development :: Libraries :: Python Modules
Classifier: License :: OSI Approved :: Apache Software License
Classifier: Framework :: Django :: 1.5
Classifier: Framework :: Django :: 1.6
Classifier: Framework :: Django :: 1.7
Classifier: Framework :: Django :: 1.8
Classifier: Framework :: Django :: 1.9
Classifier: Framework :: Django :: 1.10
Classifier: Programming Language :: Python :: 2
Classifier: Programming Language :: Python :: 2.6
Classifier: Programming Language :: Python :: 2.7
Classifier: Programming Language :: Python :: 3
Classifier: Programming Language :: Python :: 3.3
Classifier: Programming Language :: Python :: 3.4
Classifier: Programming Language :: Python :: 3.5
Classifier: Programming Language :: Python :: 3.6
